{
  "name": "page_home",
  "page_id": "page_home",
  "glb_ctl_cfg": false,
  "datasource": {
    "method": "",
    "params": [],
    "adapter": [],
    "data": {}
  },
  "setEvent": [],
  "configs": [],
  "auto_start_controls": [
    "page_home_ActionBarWidget_0",
    "page_home_PagerWidget_0"
  ],
  "position": [],
  "attr": [],
  "controls": [
    {
      "control_id": "page_home_PagerWidget_0",
      "xtype": "PagerWidget",
      "layout": "",
      "script": false,
      "datasource": {
        "method": "",
        "cache": "",
        "params": [],
        "adapter": [],
        "data": {
          "pagerCount": 200,
          "offset": 0,
          "itemPageName": "page_home_pager"
        }
      },
      "setEvent": [],
      "configs": [],
      "attr": [],
      "auto_start_controls": false,
      "position": [
        {
          "key": "parent",
          "value": "activity_item_container_llayout"
        },
        {
          "key": "location",
          "value": "0"
        },
        {
          "key": "insertType",
          "value": "1"
        }
      ]
    },
    {
      "control_id": "page_home_ActionBarWidget_0",
      "xtype": "ActionBarWidget",
      "layout": "",
      "datasource": {
        "method": "",
        "params": [],
        "adapter": [],
        "data": {
          "actionBarBg": "#FFf9f9f9",
          "homeIcon": "webview/images/icon/default/setting.png",
          "title": "今天",
          "titleIcon": "justClick",
          "withActionBar": "true",
          "menuItemsData": {
            "menuList": [
              {
                "itemId": "action_bar_menu_item_gen",
                "clickTag": "1",
                "title": "扫一扫",
                "iconName": "webview/images/icon/default/menu_qr.png",
                "showAsAction": "never"
              },
              {
                "itemId": "action_bar_menu_item_gen",
                "clickTag": "2",
                "title": "搜索课程",
                "iconName": "webview/images/icon/default/menu_search.png",
                "showAsAction": "never"
              },
              {
                "itemId": "action_bar_menu_item_gen",
                "clickTag": "4",
                "title": "设置时间",
                "iconName": "webview/images/icon/default/menu_setting.png",
                "showAsAction": "never"
              },
              {
                "itemId": "action_bar_menu_item_gen",
                "clickTag": "5",
                "title": "我的",
                "iconName": "webview/images/icon/default/menu_feedback.png",
                "showAsAction": "never"
              }
            ]
          }
        }
      },
      "setEvent": [],
      "configs": [],
      "auto_start_controls": false,
      "position": [],
      "attr": []
    }
  ]
}